corpus_query_language/__init__.py
corpus_query_language/core/__init__.py
corpus_query_language/core/core.py
corpus_query_language/engine/__init__.py
corpus_query_language/engine/engine.py
corpus_query_language/language/__init__.py
corpus_query_language/language/lexer.py
corpus_query_language/language/parser.py
corpus_query_language/utils/__init__.py
corpus_query_language/utils/utils.py
corpus_query_language-0.0.5.dist-info/licenses/LICENSE
corpus_query_language-0.0.5.dist-info/METADATA
corpus_query_language-0.0.5.dist-info/WHEEL
corpus_query_language-0.0.5.dist-info/top_level.txt
corpus_query_language-0.0.5.dist-info/RECORD
