Metadata-Version: 2.4
Name: corpus-query-language
Version: 0.0.5
Summary: A small example package
Author-email: Matthias Gille Levenson <matthias.gille-levenson@ens-lyon.fr>
License-Expression: CC-BY-NC-SA-4.0
Project-URL: Homepage, https://github.com/matgille/CQL
Project-URL: Issues, https://github.com/matgille/CQL/issues
Classifier: Programming Language :: Python :: 3
Classifier: Operating System :: OS Independent
Requires-Python: >=3.9
License-File: LICENSE
Requires-Dist: ply
Dynamic: license-file
